{
  "hash": "8266169eaf1f7c4d8ed2ae375e5466fd",
  "result": {
    "engine": "knitr",
    "markdown": "---\ntitle: \"ReproRes Poll Class 05\"\noutput: \n  flexdashboard::flex_dashboard:\n    orientation: rows\n    vertical_layout: scroll\n    theme: yeti\n---\n\n\n\n[Take the Poll](https://forms.gle/yee8TwyKn5PefPkK7)\n\n\n\n\n\n::: {.cell}\n\n:::\n\n::: {.cell}\n\n:::\n\n\n\n32 Participants\n\nRow {data-height=400}\n-----------------------------------------------------------------------\n\n### How did you engage with Chapter 5?\n\n\n\n::: {.cell}\n::: {.cell-output-display}\n![](poll-05_files/figure-html/unnamed-chunk-3-1.png){width=960}\n:::\n:::\n\n\n\n### #GreatPsychPumpkinBattle\n\n\n\n::: {.cell}\n::: {.cell-output-display}\n![](poll-05_files/figure-html/unnamed-chunk-4-1.png){width=960}\n:::\n:::\n\n\n\n### Extra Help\n\n\n\n::: {.cell}\n::: {.cell-output-display}\n![](poll-05_files/figure-html/unnamed-chunk-5-1.png){width=960}\n:::\n:::\n\n\n\n\nRow {data-height=400}\n-----------------------------------------------------------------------\n\n### List concepts you learned in Chapter 5 that you feel confident about.\n\n\n\n::: {.cell}\n::: {.cell-output-display}\n![](poll-05_files/figure-html/unnamed-chunk-6-1.png){width=960}\n:::\n:::\n\n\n\n\n\n### List concepts you learned in Chapter 5 that you feel less confident about and would like reviewed in class today.\n\n\n\n::: {.cell}\n::: {.cell-output-display}\n![](poll-05_files/figure-html/unnamed-chunk-7-1.png){width=960}\n:::\n:::\n\n\n\nRow {data-height=600}\n-----------------------------------------------------------------------\n\n### Confident \n\n\n\n::: {.cell}\n::: {.cell-output-display}\n`````{=html}\n<table class=\" lightable-classic lightable-striped\" style='font-family: \"Arial Narrow\", \"Source Sans Pro\", sans-serif; margin-left: auto; margin-right: auto;'>\n <thead>\n  <tr>\n   <th style=\"text-align:left;\">  </th>\n  </tr>\n </thead>\n<tbody>\n  <tr>\n   <td style=\"text-align:left;\"> basic joins </td>\n  </tr>\n  <tr>\n   <td style=\"text-align:left;\"> joining data, separating data </td>\n  </tr>\n  <tr>\n   <td style=\"text-align:left;\"> all of it </td>\n  </tr>\n  <tr>\n   <td style=\"text-align:left;\"> Data merging </td>\n  </tr>\n  <tr>\n   <td style=\"text-align:left;\"> combo tables </td>\n  </tr>\n  <tr>\n   <td style=\"text-align:left;\"> left and right join </td>\n  </tr>\n  <tr>\n   <td style=\"text-align:left;\"> All of them :) </td>\n  </tr>\n  <tr>\n   <td style=\"text-align:left;\"> mutating joins, filtering joins, binding joins, 3 set operations </td>\n  </tr>\n  <tr>\n   <td style=\"text-align:left;\"> Joining data </td>\n  </tr>\n  <tr>\n   <td style=\"text-align:left;\"> All </td>\n  </tr>\n  <tr>\n   <td style=\"text-align:left;\"> NA </td>\n  </tr>\n  <tr>\n   <td style=\"text-align:left;\"> joining verbs </td>\n  </tr>\n  <tr>\n   <td style=\"text-align:left;\"> joins </td>\n  </tr>\n  <tr>\n   <td style=\"text-align:left;\"> Merging tables together following various criteria </td>\n  </tr>\n  <tr>\n   <td style=\"text-align:left;\"> joins </td>\n  </tr>\n  <tr>\n   <td style=\"text-align:left;\"> mutating join verbs </td>\n  </tr>\n  <tr>\n   <td style=\"text-align:left;\"> anti_join lol </td>\n  </tr>\n  <tr>\n   <td style=\"text-align:left;\"> mutating, filtering, binding joins </td>\n  </tr>\n  <tr>\n   <td style=\"text-align:left;\"> merging </td>\n  </tr>\n  <tr>\n   <td style=\"text-align:left;\"> Set Operations </td>\n  </tr>\n  <tr>\n   <td style=\"text-align:left;\"> combine tibbles </td>\n  </tr>\n  <tr>\n   <td style=\"text-align:left;\"> Mutating joins </td>\n  </tr>\n  <tr>\n   <td style=\"text-align:left;\"> binding joints, filtering joins </td>\n  </tr>\n  <tr>\n   <td style=\"text-align:left;\"> join </td>\n  </tr>\n  <tr>\n   <td style=\"text-align:left;\"> almost everything </td>\n  </tr>\n</tbody>\n</table>\n\n`````\n:::\n:::\n\n\n\n\n### Not Confident \n\n\n\n::: {.cell}\n::: {.cell-output-display}\n`````{=html}\n<table class=\" lightable-classic lightable-striped\" style='font-family: \"Arial Narrow\", \"Source Sans Pro\", sans-serif; margin-left: auto; margin-right: auto;'>\n <thead>\n  <tr>\n   <th style=\"text-align:left;\">  </th>\n  </tr>\n </thead>\n<tbody>\n  <tr>\n   <td style=\"text-align:left;\"> suffix, order in anti joins </td>\n  </tr>\n  <tr>\n   <td style=\"text-align:left;\"> n/a </td>\n  </tr>\n  <tr>\n   <td style=\"text-align:left;\"> Basic set up </td>\n  </tr>\n  <tr>\n   <td style=\"text-align:left;\"> inner join </td>\n  </tr>\n  <tr>\n   <td style=\"text-align:left;\"> - </td>\n  </tr>\n  <tr>\n   <td style=\"text-align:left;\"> None </td>\n  </tr>\n  <tr>\n   <td style=\"text-align:left;\"> NA </td>\n  </tr>\n  <tr>\n   <td style=\"text-align:left;\"> difference between left/right_join and full join </td>\n  </tr>\n  <tr>\n   <td style=\"text-align:left;\"> filtering, set operations </td>\n  </tr>\n  <tr>\n   <td style=\"text-align:left;\"> semi_join, left_join etc. </td>\n  </tr>\n  <tr>\n   <td style=\"text-align:left;\"> set operations </td>\n  </tr>\n  <tr>\n   <td style=\"text-align:left;\"> details </td>\n  </tr>\n  <tr>\n   <td style=\"text-align:left;\"> Mutating Joins and Filtering Joins </td>\n  </tr>\n  <tr>\n   <td style=\"text-align:left;\"> no </td>\n  </tr>\n  <tr>\n   <td style=\"text-align:left;\"> Binding joins, set operations </td>\n  </tr>\n  <tr>\n   <td style=\"text-align:left;\"> manipulate table </td>\n  </tr>\n</tbody>\n</table>\n\n`````\n:::\n:::\n",
    "supporting": [
      "poll-05_files"
    ],
    "filters": [
      "rmarkdown/pagebreak.lua"
    ],
    "includes": {
      "include-in-header": [
        "<script src=\"../site_libs/kePrint-0.0.1/kePrint.js\"></script>\n<link href=\"../site_libs/lightable-0.0.1/lightable.css\" rel=\"stylesheet\" />\n"
      ]
    },
    "engineDependencies": {},
    "preserve": {},
    "postProcess": true
  }
}